openmldb_chatgpt/__init__.py
openmldb_chatgpt/cli.py
openmldb_chatgpt/config_util.py
openmldb_chatgpt/gpt_manager.py
openmldb_chatgpt/help_util.py
openmldb_chatgpt/openmldb_manager.py
openmldb_chatgpt/print_util.py
openmldb_chatgpt/sql_util.py
openmldb_chatgpt-0.1.1.dist-info/LICENSE
openmldb_chatgpt-0.1.1.dist-info/METADATA
openmldb_chatgpt-0.1.1.dist-info/WHEEL
openmldb_chatgpt-0.1.1.dist-info/entry_points.txt
openmldb_chatgpt-0.1.1.dist-info/top_level.txt
openmldb_chatgpt-0.1.1.dist-info/RECORD
